vitbackbone/__init__.py
vitbackbone/main.py
vitbackbone/models/__init__.py
vitbackbone/models/swin/__init__.py
vitbackbone/models/swin/build.py
vitbackbone/models/swin/swin_transformer.py
vitbackbone/models/swin/utils.py
vitbackbone/models/van/__init__.py
vitbackbone/models/van/utils.py
vitbackbone/models/van/van.py
vitbackbone-1.0.2.dist-info/METADATA
vitbackbone-1.0.2.dist-info/WHEEL
vitbackbone-1.0.2.dist-info/top_level.txt
vitbackbone-1.0.2.dist-info/RECORD
