Metadata-Version: 2.1
Name: vitbackbone
Version: 1.0.2
Summary: Build your own model quickly based on Vision Transformer backbone
Home-page: UNKNOWN
Author: jintuzheng
Author-email: jintuzheng@outlook.com
License: apache 3.0
Platform: UNKNOWN
Requires: numpy
Requires: timm
Requires: torch
